LICENSE
README.md
setup.py
wechat/__init__.py
wechat/crypt.py
wechat/enterprise.py
wechat/models.py
wechat/official.py
youhat.egg-info/PKG-INFO
youhat.egg-info/SOURCES.txt
youhat.egg-info/dependency_links.txt
youhat.egg-info/requires.txt
youhat.egg-info/top_level.txt